test/__init__.py
test/test_sample.py
test/crypto/__init__.py
test/crypto/conftest.py
test/crypto/test_crypto.py
test/exploratory/__init__.py
test/exploratory/test_cryptography.py
zteb/__about__.py
zteb/__init__.py
zteb/exceptions.py
zteb/utils.py
zteb/cards/__init__.py
zteb/cards/tony-birthday-card.zteb
zteb/cli/__init__.py
zteb/cli/argtype.py
zteb/cli/main.py
zteb/cli/unwrap.py
zteb/cli/wrap.py
zteb/crypto/__init__.py
zteb/crypto/primes.py
zteb/crypto/puzzle.py
zteb/crypto/symmetric.py
zteb-0.1.1.dist-info/LICENSE.txt
zteb-0.1.1.dist-info/METADATA
zteb-0.1.1.dist-info/WHEEL
zteb-0.1.1.dist-info/entry_points.txt
zteb-0.1.1.dist-info/top_level.txt
zteb-0.1.1.dist-info/RECORD
