Metadata-Version: 2.1
Name: zteb
Version: 0.1.1
Summary: ZTEB is Tony's Electronic Birthday-Card
Home-page: https://github.com/BoyanH/ZTEB
Author: Boyan Hristov
License: SEE LICENSE IN LICENSE.txt
Platform: UNKNOWN
Requires-Python: >=3.8
Requires-Dist: cryptography
Requires-Dist: tqdm
Requires-Dist: click
Requires-Dist: pandas
